Nanybot/How.py
Nanybot/Ny_Wb.py
Nanybot/client.py
Nanybot/encryption.py
Nanybot-1.0.0.dist-info/LICENCE
Nanybot-1.0.0.dist-info/METADATA
Nanybot-1.0.0.dist-info/WHEEL
Nanybot-1.0.0.dist-info/top_level.txt
Nanybot-1.0.0.dist-info/RECORD
